odoo/addons/web_widget_x2many_2d_matrix_example/README.rst
odoo/addons/web_widget_x2many_2d_matrix_example/__init__.py
odoo/addons/web_widget_x2many_2d_matrix_example/__manifest__.py
odoo/addons/web_widget_x2many_2d_matrix_example/demo/x2m.demo.csv
odoo/addons/web_widget_x2many_2d_matrix_example/models/__init__.py
odoo/addons/web_widget_x2many_2d_matrix_example/models/x2m_demo.py
odoo/addons/web_widget_x2many_2d_matrix_example/security/ir.model.access.csv
odoo/addons/web_widget_x2many_2d_matrix_example/views/x2m_demo.xml
odoo/addons/web_widget_x2many_2d_matrix_example/wizard/__init__.py
odoo/addons/web_widget_x2many_2d_matrix_example/wizard/demo_wizard.py
odoo/addons/web_widget_x2many_2d_matrix_example/wizard/x2m_matrix.xml
odoo11_addon_web_widget_x2many_2d_matrix_example-11.0.1.0.0.dist-info/DESCRIPTION.rst
odoo11_addon_web_widget_x2many_2d_matrix_example-11.0.1.0.0.dist-info/METADATA
odoo11_addon_web_widget_x2many_2d_matrix_example-11.0.1.0.0.dist-info/RECORD
odoo11_addon_web_widget_x2many_2d_matrix_example-11.0.1.0.0.dist-info/WHEEL
odoo11_addon_web_widget_x2many_2d_matrix_example-11.0.1.0.0.dist-info/metadata.json
odoo11_addon_web_widget_x2many_2d_matrix_example-11.0.1.0.0.dist-info/top_level.txt
